{
  "video_name": "Abuse034_x264",
  "npz_path": "data/UCF-Crime-DVS/Abuse/Abuse034_x264.npz",
  "active_windows": [
    [
      1.80770293,
      3.6078368600000004
    ],
    [
      7.7224287,
      8.23675268
    ],
    [
      12.351344520000001,
      12.8656685
    ],
    [
      20.32336621,
      20.83769019
    ],
    [
      38.839029489999994,
      40.639163419999996
    ],
    [
      47.58253715,
      49.639833069999995
    ]
  ],
  "coverage_percent": 14.0,
  "total_duration_sec": 51.43,
  "evaluation_success": true
}